gufo/err/__init__.py
gufo/err/cli.py
gufo/err/codec.py
gufo/err/compressor.py
gufo/err/err.py
gufo/err/frame.py
gufo/err/logger.py
gufo/err/py.typed
gufo/err/types.py
gufo/err/abc/__init__.py
gufo/err/abc/failfast.py
gufo/err/abc/formatter.py
gufo/err/abc/middleware.py
gufo/err/failfast/__init__.py
gufo/err/failfast/always.py
gufo/err/failfast/never.py
gufo/err/failfast/typematch.py
gufo/err/failfast/types.py
gufo/err/formatter/__init__.py
gufo/err/formatter/extend.py
gufo/err/formatter/loader.py
gufo/err/formatter/terse.py
gufo/err/middleware/__init__.py
gufo/err/middleware/errorinfo.py
gufo/err/middleware/sentry.py
gufo/err/middleware/traceback.py
gufo_err-0.6.0.dist-info/licenses/LICENSE.md
gufo_err-0.6.0.dist-info/METADATA
gufo_err-0.6.0.dist-info/WHEEL
gufo_err-0.6.0.dist-info/entry_points.txt
gufo_err-0.6.0.dist-info/top_level.txt
gufo_err-0.6.0.dist-info/RECORD
